{
  "id": "0003_reset_analytics",
  "prevId": "0002_shiny_maestro",
  "version": "7",
  "dialect": "postgresql",
  "tables": {
    "public.users": {
      "name": "users",
      "schema": "",
      "columns": {
        "id": {
          "name": "id",
          "type": "uuid",
          "primaryKey": true,
          "notNull": true,
          "default": "gen_random_uuid()"
        },
        "name": {
          "name": "name",
          "type": "varchar(255)",
          "primaryKey": false,
          "notNull": true
        },
        "email": {
          "name": "email",
          "type": "varchar(255)",
          "primaryKey": false,
          "notNull": true
        },
        "created_at": {
          "name": "created_at",
          "type": "timestamp with time zone",
          "primaryKey": false,
          "notNull": true,
          "default": "now()"
        },
        "updated_at": {
          "name": "updated_at",
          "type": "timestamp with time zone",
          "primaryKey": false,
          "notNull": true,
          "default": "now()"
        }
      },
      "indexes": {},
      "foreignKeys": {},
      "compositePrimaryKeys": {},
      "uniqueConstraints": {
        "users_email_unique": {
          "name": "users_email_unique",
          "nullsNotDistinct": false,
          "columns": ["email"]
        }
      }
    },
    "public.bmi_records": {
      "name": "bmi_records",
      "schema": "",
      "columns": {
        "id": {
          "name": "id",
          "type": "uuid",
          "primaryKey": true,
          "notNull": true,
          "default": "gen_random_uuid()"
        },
        "user_id": {
          "name": "user_id",
          "type": "uuid",
          "primaryKey": false,
          "notNull": true
        },
        "weight": {
          "name": "weight",
          "type": "numeric(5, 2)",
          "primaryKey": false,
          "notNull": true
        },
        "height": {
          "name": "height",
          "type": "numeric(5, 2)",
          "primaryKey": false,
          "notNull": true
        },
        "bmi_value": {
          "name": "bmi_value",
          "type": "numeric(4, 2)",
          "primaryKey": false,
          "notNull": true
        },
        "recorded_at": {
          "name": "recorded_at",
          "type": "timestamp with time zone",
          "primaryKey": false,
          "notNull": true,
          "default": "now()"
        },
        "created_at": {
          "name": "created_at",
          "type": "timestamp with time zone",
          "primaryKey": false,
          "notNull": true,
          "default": "now()"
        },
        "updated_at": {
          "name": "updated_at",
          "type": "timestamp with time zone",
          "primaryKey": false,
          "notNull": true,
          "default": "now()"
        }
      },
      "indexes": {},
      "foreignKeys": {
        "bmi_records_user_id_users_id_fk": {
          "name": "bmi_records_user_id_users_id_fk",
          "tableFrom": "bmi_records",
          "tableTo": "users",
          "columnsFrom": ["user_id"],
          "columnsTo": ["id"],
          "onDelete": "cascade",
          "onUpdate": "no action"
        }
      },
      "compositePrimaryKeys": {},
      "uniqueConstraints": {}
    },
    "public.qr_scans": {
      "name": "qr_scans",
      "schema": "",
      "columns": {
        "id": {
          "name": "id",
          "type": "uuid",
          "primaryKey": true,
          "notNull": true,
          "default": "gen_random_uuid()"
        },
        "user_id": {
          "name": "user_id",
          "type": "uuid",
          "primaryKey": false,
          "notNull": false
        },
        "exercise_path": {
          "name": "exercise_path",
          "type": "varchar(500)",
          "primaryKey": false,
          "notNull": true
        },
        "exercise_name": {
          "name": "exercise_name",
          "type": "varchar(255)",
          "primaryKey": false,
          "notNull": false
        },
        "equipment_type": {
          "name": "equipment_type",
          "type": "varchar(100)",
          "primaryKey": false,
          "notNull": false
        },
        "session_id": {
          "name": "session_id",
          "type": "varchar(255)",
          "primaryKey": false,
          "notNull": true
        },
        "user_agent": {
          "name": "user_agent",
          "type": "varchar(500)",
          "primaryKey": false,
          "notNull": false
        },
        "ip_address": {
          "name": "ip_address",
          "type": "varchar(45)",
          "primaryKey": false,
          "notNull": false
        },
        "scanned_at": {
          "name": "scanned_at",
          "type": "timestamp with time zone",
          "primaryKey": false,
          "notNull": true,
          "default": "now()"
        }
      },
      "indexes": {},
      "foreignKeys": {
        "qr_scans_user_id_users_id_fk": {
          "name": "qr_scans_user_id_users_id_fk",
          "tableFrom": "qr_scans",
          "tableTo": "users",
          "columnsFrom": ["user_id"],
          "columnsTo": ["id"],
          "onDelete": "set null",
          "onUpdate": "no action"
        }
      },
      "compositePrimaryKeys": {},
      "uniqueConstraints": {}
    }
  },
  "enums": {},
  "schemas": {},
  "_meta": {
    "columns": {},
    "schemas": {},
    "tables": {}
  }
}
